osamarahmani/__init__.py
osamarahmani-2.0.0.dist-info/METADATA
osamarahmani-2.0.0.dist-info/WHEEL
osamarahmani-2.0.0.dist-info/RECORD
