Metadata-Version: 2.4
Name: osamarahmani
Version: 2.0.0
Summary: Public profile info for Osama Rahmani
Author-email: Osama Rahmani <osamrahmani.tech@gmail.com>
Requires-Python: >=3.7
